antchain_sdk_ak_d34765e5ce404706a4e60e213daf08f5/__init__.py
antchain_sdk_ak_d34765e5ce404706a4e60e213daf08f5/client.py
antchain_sdk_ak_d34765e5ce404706a4e60e213daf08f5/models.py
antchain_ak_d34765e5ce404706a4e60e213daf08f5-1.0.2.dist-info/LICENSE
antchain_ak_d34765e5ce404706a4e60e213daf08f5-1.0.2.dist-info/METADATA
antchain_ak_d34765e5ce404706a4e60e213daf08f5-1.0.2.dist-info/WHEEL
antchain_ak_d34765e5ce404706a4e60e213daf08f5-1.0.2.dist-info/top_level.txt
antchain_ak_d34765e5ce404706a4e60e213daf08f5-1.0.2.dist-info/RECORD
